Metadata-Version: 2.1
Name: dsdl
Version: 0.1.10.11
Summary: Python SDK for DSDL
Author: DSDL team
Author-email: dsdl-team@pjlab.org.cn
Classifier: Programming Language :: Python :: 3.8
Classifier: Programming Language :: Python :: 3.9
Classifier: Programming Language :: Python :: 3.10
Requires-Python: >=3.8
License-File: LICENSE
Requires-Dist: pyyaml (>=6.0)
Requires-Dist: click (>=8.1.3)
Requires-Dist: networkx (>=2.8.4)
Requires-Dist: Pillow (>=9.1.0)
Requires-Dist: prettytable (>=3.3.0)
Requires-Dist: opencv-python (>=4.6.0.66)
Requires-Dist: jsonmodels (==2.6.0)
Requires-Dist: environs (==9.5.0)
Requires-Dist: pylint (>=2.15.5)
Requires-Dist: fastjsonschema (>=2.16.3)
Requires-Dist: jsonschema (>=3.2.0)
Requires-Dist: psutil (>=5.9.0)
Requires-Dist: tqdm (>=4.65.0)
Requires-Dist: tifffile
Requires-Dist: terminaltables (>=3.1.10)
Requires-Dist: matplotlib (>=3.3.3)
